hypomnema/__init__.py
hypomnema/py.typed
hypomnema/base/__init__.py
hypomnema/base/errors.py
hypomnema/base/types.py
hypomnema/xml/__init__.py
hypomnema/xml/constants.py
hypomnema/xml/policy.py
hypomnema/xml/utils.py
hypomnema/xml/backends/__init__.py
hypomnema/xml/backends/base.py
hypomnema/xml/backends/lxml.py
hypomnema/xml/backends/standard.py
hypomnema/xml/deserialization/__init__.py
hypomnema/xml/deserialization/_handlers.py
hypomnema/xml/deserialization/base.py
hypomnema/xml/deserialization/deserializer.py
hypomnema/xml/serialization/__init__.py
hypomnema/xml/serialization/_handlers.py
hypomnema/xml/serialization/base.py
hypomnema/xml/serialization/serializer.py
hypomnema-0.4.4.dist-info/licenses/LICENSE
hypomnema-0.4.4.dist-info/METADATA
hypomnema-0.4.4.dist-info/WHEEL
hypomnema-0.4.4.dist-info/top_level.txt
hypomnema-0.4.4.dist-info/RECORD
